voicestudio/adapters/config.py
voicestudio/config/__init__.py
voicestudio/config/synthesis_config.py
voicestudio/datasets/__init__.py
voicestudio/datasets/base.py
voicestudio/datasets/libritts.py
voicestudio/datasets/libritts_p.py
voicestudio/datasets/libritts_p2.py
voicestudio/datasets/ljspeech.py
voicestudio/datasets/vctk.py
voicestudio/metrics/__init__.py
voicestudio/metrics/base.py
voicestudio/metrics/ffe.py
voicestudio/metrics/mcd.py
voicestudio/metrics/sim.py
voicestudio/metrics/utmos.py
voicestudio/metrics/wer.py
voicestudio/metrics/strategies/__init__.py
voicestudio/metrics/strategies/base.py
voicestudio/metrics/strategies/method1.py
voicestudio/metrics/strategies/method2.py
voicestudio/metrics/strategies/method3.py
voicestudio/models/integrations/__init__.py
voicestudio/models/integrations/base.py
voicestudio/models/integrations/chatterbox_tts.py
voicestudio/models/integrations/dia_tts.py
voicestudio/models/integrations/higgs_v2.py
voicestudio/models/integrations/parler_tts.py
voicestudio/models/integrations/xtts.py
voicestudio/utils/__init__.py
voicestudio/utils/attention_map.py
voicestudio/utils/evaluate.py
voicestudio/utils/losses.py
voicestudio/utils/synthesize.py
voicestudio/utils/trainer.py
voicestudio-1.0.0.dist-info/METADATA
voicestudio-1.0.0.dist-info/WHEEL
voicestudio-1.0.0.dist-info/licenses/LICENSE
voicestudio-1.0.0.dist-info/RECORD
