Metadata-Version: 2.4
Name: voicestudio
Version: 1.0.0
Summary: VoiceStudio: A unified toolkit for text-style prompted speech synthesis, voice adaptation, and editing
Project-URL: Homepage, https://github.com/LatentForge/VoiceStudio
Project-URL: Repository, https://github.com/LatentForge/VoiceStudio
Author-email: LatentForge <brew.airesearch@gmail.com>
License: MIT
License-File: LICENSE
Keywords: audio-generation,hypernetworks,lora,text-to-speech,voice-synthesis
Classifier: Development Status :: 3 - Alpha
Classifier: Intended Audience :: Developers
Classifier: Intended Audience :: Science/Research
Classifier: License :: OSI Approved :: MIT License
Classifier: Operating System :: OS Independent
Classifier: Programming Language :: Python :: 3
Classifier: Programming Language :: Python :: 3.11
Classifier: Programming Language :: Python :: 3.12
Classifier: Programming Language :: Python :: 3.13
Classifier: Programming Language :: Python :: 3.14
Classifier: Topic :: Multimedia :: Sound/Audio :: Speech
Classifier: Topic :: Scientific/Engineering :: Artificial Intelligence
Requires-Python: >=3.11
Requires-Dist: accelerate>=1.10.0
Requires-Dist: datasets>=4.0.0
Requires-Dist: hf-xet>=1.1.8
Requires-Dist: ipywidgets>=8.1.7
Requires-Dist: librosa>=0.11.0
Requires-Dist: matplotlib>=3.10.5
Requires-Dist: notebook>=7.4.5
Requires-Dist: peft>=0.18.0
Requires-Dist: torch; platform_system == 'Windows'
Requires-Dist: torch>=2.8.0
Requires-Dist: torchaudio; platform_system == 'Windows'
Requires-Dist: torchaudio>=2.8.0
Requires-Dist: torchcodec>=0.9.1
Requires-Dist: tqdm>=4.67.1
Requires-Dist: transformers>=5.0.0rc1
Requires-Dist: wandb>=0.21.1
Provides-Extra: all
Requires-Dist: voicestudio-higgs-audio; extra == 'all'
Requires-Dist: voicestudio-parler-tts; extra == 'all'
Provides-Extra: higgs
Requires-Dist: voicestudio-higgs-audio; extra == 'higgs'
Provides-Extra: parler
Requires-Dist: voicestudio-parler-tts; extra == 'parler'
Provides-Extra: web
Requires-Dist: fastapi>=0.126.0; extra == 'web'
